CHANGES.txt
MANIFEST.in
README.txt
setup.py
src/rsl/__init__.py
src/rsl.wsdl1.egg-info/PKG-INFO
src/rsl.wsdl1.egg-info/SOURCES.txt
src/rsl.wsdl1.egg-info/dependency_links.txt
src/rsl.wsdl1.egg-info/entry_points.txt
src/rsl.wsdl1.egg-info/namespace_packages.txt
src/rsl.wsdl1.egg-info/requires.txt
src/rsl.wsdl1.egg-info/top_level.txt
src/rsl/wsdl1/__init__.py
src/rsl/wsdl1/binding.py
src/rsl/wsdl1/factories.py
src/rsl/wsdl1/interfaces.py
src/rsl/wsdl1/namespace.py
src/rsl/wsdl1/schema.py
src/rsl/wsdl1/wsdl.py
src/rsl/wsdl1/xsds/wsdl.xsd